{
  "@id" : "de09b8cc-6ced-4aa4-b529-fcb371a4e6ed",
  "turisti" : [ {
    "@type" : "Turista",
    "@id" : "f2c77d68-ae8c-4b47-9780-d017443b395e",
    "korIme" : "ognjen",
    "lozinka" : "ognjen",
    "ime" : "Ognjen",
    "prezime" : "Ognjenovic",
    "telefon" : "0656874164",
    "komentari" : [ ],
    "rezervacije" : [ ]
  }, {
    "@type" : "Turista",
    "@id" : "8386d079-6086-4d21-b4fa-18d0a8c6e441",
    "korIme" : "ana",
    "lozinka" : "ana",
    "ime" : "Ana",
    "prezime" : "Anic",
    "telefon" : "06998746519",
    "komentari" : [ ],
    "rezervacije" : [ ]
  } ],
  "vodici" : [ {
    "@type" : "Vodic",
    "@id" : "25ede98a-d105-49b3-90a3-3adf410ee74d",
    "korIme" : "janko",
    "lozinka" : "janko",
    "ime" : "Janko",
    "prezime" : "Jankovic",
    "telefon" : "0698874621",
    "komentari" : [ ],
    "rezervacije" : [ ],
    "ture" : [ {
      "@id" : "65a3a8ff-dc8e-48b8-bb63-877d1b2ab246",
      "idTure" : "Kavos-nikad ne spava",
      "opis" : "10 neispavanih noci",
      "ocena" : 0,
      "minBrojMesta" : 20,
      "kreatorTure" : "25ede98a-d105-49b3-90a3-3adf410ee74d",
      "vodici" : [ "25ede98a-d105-49b3-90a3-3adf410ee74d", {
        "@type" : "Vodic",
        "@id" : "7307db01-4c3e-4b08-932a-f7fb34aa3a46",
        "korIme" : "milan",
        "lozinka" : "milan",
        "ime" : "Milan",
        "prezime" : "Milanovic",
        "telefon" : "0654916984",
        "komentari" : [ ],
        "rezervacije" : [ ],
        "ture" : [ {
          "@id" : "57a915ad-c52c-454c-9009-5ab6ed6acede",
          "idTure" : "Zlatibor-5 dana",
          "opis" : "odmor u prirodi",
          "ocena" : 7,
          "minBrojMesta" : 20,
          "kreatorTure" : "7307db01-4c3e-4b08-932a-f7fb34aa3a46",
          "vodici" : [ "25ede98a-d105-49b3-90a3-3adf410ee74d", "7307db01-4c3e-4b08-932a-f7fb34aa3a46" ],
          "termini" : [ ],
          "komentari" : [ ],
          "gradovi" : [ {
            "@id" : "874f8c0c-349d-40ca-afba-88f21afc720f",
            "naziv" : "Zlatibor",
            "ptt" : 22240
          } ],
          "destinacije" : [ {
            "@id" : "643d15dd-a1d3-4e5d-b14f-92603e5ae4c5",
            "naziv" : "Mokra Gora",
            "opis" : "selo",
            "mesto" : "874f8c0c-349d-40ca-afba-88f21afc720f"
          } ]
        }, "65a3a8ff-dc8e-48b8-bb63-877d1b2ab246" ]
      }, {
        "@type" : "Vodic",
        "@id" : "9563ac39-396b-43b0-b302-a738ff039c0e",
        "korIme" : "igor",
        "lozinka" : "igor",
        "ime" : "Igor",
        "prezime" : "Igic",
        "telefon" : "011561565",
        "komentari" : [ ],
        "rezervacije" : [ ],
        "ture" : [ "65a3a8ff-dc8e-48b8-bb63-877d1b2ab246" ]
      } ],
      "termini" : [ {
        "@id" : "6b497bd8-57b5-48b5-8210-5da0cddcf1c7",
        "aktivnoStanje" : {
          "class" : "model.Aktivan",
          "@id" : "34115a79-1538-4515-9d9e-a00f47f38ddb",
          "termin" : null
        },
        "tura" : "65a3a8ff-dc8e-48b8-bb63-877d1b2ab246",
        "pocetakTure" : "30.6.2017",
        "krajTure" : "10.7.2017",
        "brojSlobodnihMesta" : 50,
        "aktivan" : false,
        "cena" : 200.0,
        "rezervacije" : [ ]
      }, {
        "@id" : "87d2516b-ee95-417a-bd78-f116dc805acb",
        "aktivnoStanje" : {
          "class" : "model.Aktivan",
          "@id" : "1dfbd32a-9b94-423f-9b0c-b257cd7f41bc",
          "termin" : "87d2516b-ee95-417a-bd78-f116dc805acb"
        },
        "tura" : "65a3a8ff-dc8e-48b8-bb63-877d1b2ab246",
        "pocetakTure" : "15.7.2017",
        "krajTure" : "25.7.2017",
        "brojSlobodnihMesta" : 50,
        "aktivan" : true,
        "cena" : 250.0,
        "rezervacije" : [ ]
      } ],
      "komentari" : [ ],
      "gradovi" : [ {
        "@id" : "3e489390-76ba-49d6-a8a8-85c754dadcb8",
        "naziv" : "Kavos",
        "ptt" : 5458
      } ],
      "destinacije" : [ {
        "@id" : "31424c78-e353-4060-affc-ab786bd94d38",
        "naziv" : "Srpska kuca",
        "opis" : "muzej",
        "mesto" : {
          "@id" : "ef781e74-3467-4863-8768-4fad4c79a768",
          "naziv" : "Krf",
          "ptt" : 5458
        }
      } ]
    }, "57a915ad-c52c-454c-9009-5ab6ed6acede" ]
  }, "7307db01-4c3e-4b08-932a-f7fb34aa3a46", "9563ac39-396b-43b0-b302-a738ff039c0e" ],
  "ture" : [ "65a3a8ff-dc8e-48b8-bb63-877d1b2ab246", "57a915ad-c52c-454c-9009-5ab6ed6acede" ]
}